ngshare/__init__.py
ngshare/__main__.py
ngshare/alembic.ini
ngshare/dbutil.py
ngshare/dump.html
ngshare/favicon.ico
ngshare/home.html
ngshare/masonry.min.js
ngshare/ngshare.py
ngshare/test_dbutil.py
ngshare/test_ngshare.py
ngshare/version.py
ngshare/vngshare.py
ngshare/alembic/env.py
ngshare/alembic/script.py.mako
ngshare/alembic/versions/1921a169739b_add_file_size.py
ngshare/alembic/versions/aa00db20c10a_init.py
ngshare/database/__init__.py
ngshare/database/database.py
ngshare/database/test_database.py
ngshare-0.6.0.dist-info/LICENSE
ngshare-0.6.0.dist-info/METADATA
ngshare-0.6.0.dist-info/WHEEL
ngshare-0.6.0.dist-info/top_level.txt
ngshare-0.6.0.dist-info/RECORD
