Metadata-Version: 2.1
Name: ngshare
Version: 0.6.0
Summary: nbgrader sharing service
Home-page: https://github.com/LibreTexts/ngshare
Author: Team KALE
Author-email: ercli@ucdavis.edu
Classifier: Programming Language :: Python :: 3
Classifier: License :: OSI Approved :: BSD License
Classifier: Operating System :: POSIX :: Linux
Requires-Python: >=3.6
License-File: LICENSE
Requires-Dist: SQLAlchemy (>=1.3.12)
Requires-Dist: alembic (>=1.3.2)
Requires-Dist: tornado (>=6.0.3)
Requires-Dist: jupyterhub (>=1.1.0)
